<?xml version="1.0" encoding="UTF-8"?>
<mxfile host="app.diagrams.net" modified="2024-02-06T09:32:10.430Z" agent="Mozilla/5.0 (Macintosh; Intel Mac OS X 10_15_7) AppleWebKit/537.36 (KHTML, like Gecko) Chrome/121.0.0.0 Safari/537.36" version="23.1.1" etag="j8_MJ3RMcdW9zcjurfyH" type="device">
  <diagram name="Page-1" id="ZFoQsGW0uUH5cPm_rHjc">
    <mxGraphModel dx="954" dy="640" grid="1" gridSize="10" guides="1" tooltips="1" connect="1" arrows="1" fold="1" page="1" pageScale="1" pageWidth="850" pageHeight="1100" math="0" shadow="0">
      <root>
        <mxCell id="0"/>
        <mxCell id="1" parent="0"/>
        <mxCell id="2" value="Bulb burnt out" style="rhombus;whiteSpace=wrap;html=1;" vertex="1" parent="1">
          <mxGeometry x="360" y="280" width="80" height="80" as="geometry"/>
        </mxCell>
        <mxCell id="3" value="Not working" style="rhombus;whiteSpace=wrap;html=1;" vertex="1" parent="1">
          <mxGeometry x="360" y="420" width="80" height="80" as="geometry"/>
        </mxCell>
        <mxCell id="4" value="Lamp plugged in" style="rhombus;whiteSpace=wrap;html=1;" vertex="1" parent="1">
          <mxGeometry x="360" y="130" width="80" height="80" as="geometry"/>
        </mxCell>
        <mxCell id="5" value="Text" style="text;html=1;align=center;verticalAlign=middle;resizable=0;points=[];autosize=1;strokeColor=none;fillColor=none;" vertex="1" parent="1">
          <mxGeometry x="440" y="400" width="50" height="30" as="geometry"/>
        </mxCell>
        <mxCell id="6" value="" style="edgeStyle=orthogonalEdgeStyle;rounded=0;orthogonalLoop=1;jettySize=auto;html=1;" edge="1" source="7" target="4" parent="1">
          <mxGeometry relative="1" as="geometry"/>
        </mxCell>
        <mxCell id="7" value="Lamp does not work" style="rounded=1;whiteSpace=wrap;html=1;" vertex="1" parent="1">
          <mxGeometry x="340" y="40" width="120" height="40" as="geometry"/>
        </mxCell>
        <mxCell id="8" value="" style="endArrow=classic;html=1;rounded=0;" edge="1" target="3" parent="1">
          <mxGeometry width="50" height="50" relative="1" as="geometry">
            <mxPoint x="400" y="360" as="sourcePoint"/>
            <mxPoint x="450" y="310" as="targetPoint"/>
          </mxGeometry>
        </mxCell>
        <mxCell id="9" value="" style="endArrow=classic;html=1;rounded=0;" edge="1" parent="1">
          <mxGeometry width="50" height="50" relative="1" as="geometry">
            <mxPoint x="399.5" y="220" as="sourcePoint"/>
            <mxPoint x="399.5" y="280" as="targetPoint"/>
            <Array as="points">
              <mxPoint x="399.5" y="210"/>
            </Array>
          </mxGeometry>
        </mxCell>
        <mxCell id="10" value="Repair lamp" style="rounded=1;whiteSpace=wrap;html=1;" vertex="1" parent="1">
          <mxGeometry x="345" y="550" width="120" height="40" as="geometry"/>
        </mxCell>
        <mxCell id="11" value="" style="endArrow=classic;html=1;rounded=0;" edge="1" parent="1">
          <mxGeometry width="50" height="50" relative="1" as="geometry">
            <mxPoint x="400" y="500" as="sourcePoint"/>
            <mxPoint x="399.5" y="550" as="targetPoint"/>
            <Array as="points">
              <mxPoint x="399.5" y="550"/>
            </Array>
          </mxGeometry>
        </mxCell>
        <mxCell id="12" value="Plug in lamp" style="rounded=1;whiteSpace=wrap;html=1;" vertex="1" parent="1">
          <mxGeometry x="520" y="440" width="120" height="40" as="geometry"/>
        </mxCell>
        <mxCell id="13" value="Join the lamp" style="rounded=1;whiteSpace=wrap;html=1;" vertex="1" parent="1">
          <mxGeometry x="520" y="300" width="120" height="40" as="geometry"/>
        </mxCell>
        <mxCell id="14" value="Add lamps" style="rounded=1;whiteSpace=wrap;html=1;" vertex="1" parent="1">
          <mxGeometry x="520" y="150" width="120" height="40" as="geometry"/>
        </mxCell>
        <mxCell id="15" value="" style="endArrow=classic;html=1;rounded=0;" edge="1" parent="1">
          <mxGeometry width="50" height="50" relative="1" as="geometry">
            <mxPoint x="440" y="170" as="sourcePoint"/>
            <mxPoint x="520" y="170" as="targetPoint"/>
            <Array as="points">
              <mxPoint x="470" y="170"/>
            </Array>
          </mxGeometry>
        </mxCell>
        <mxCell id="16" value="" style="endArrow=classic;html=1;rounded=0;" edge="1" parent="1">
          <mxGeometry width="50" height="50" relative="1" as="geometry">
            <mxPoint x="440" y="319.5" as="sourcePoint"/>
            <mxPoint x="520" y="319.5" as="targetPoint"/>
            <Array as="points">
              <mxPoint x="470" y="319.5"/>
            
                        </Array>
          </mxGeometry>
        </mxCell>
        <mxCell id="17" value="" style="endArrow=classic;html=1;rounded=0;" edge="1" parent="1">
          <mxGeometry width="50" height="50" relative="1" as="geometry">
            <mxPoint x="440" y="459.5" as="sourcePoint"/>
            <mxPoint x="520" y="459.5" as="targetPoint"/>
            <Array as="points">
              <mxPoint x="470" y="459.5"/>
            </Array>
          </mxGeometry>
        </mxCell>
      </root>
    </mxGraphModel>
  </diagram>
</mxfile>

